{
  "from_date": "2025-01-01",
  "to_date": "2025-12-31",
  "code": "TMFR1",
  "note": "ORB long-only in SCB session windows; bk=0; min_range_atr_k=0",
  "by_param": {
    "rm20": {
      "orb_long_count": 162,
      "scb_count": 72,
      "orb_filtered_by_confluence": 90,
      "orb_long_net_total": -665.96,
      "scb_net_total": -332.05,
      "net_delta_scb_minus_orb": 333.91,
      "scb_pass_rate_of_orb": 0.4444
    },
    "rm30": {
      "orb_long_count": 143,
      "scb_count": 46,
      "orb_filtered_by_confluence": 97,
      "orb_long_net_total": -543.87,
      "scb_net_total": -138.51,
      "net_delta_scb_minus_orb": 405.36,
      "scb_pass_rate_of_orb": 0.3217
    }
  }
}